{
  "author": "rādhāmohana dāsa",
  "language": "bengali",
  "verses": "jaya jaya śrī⋅kṛṣṇacaitanya dayāsindhu\npatita uddhāra hetu jaya dīna-bandhu\n\njaya premabhaktidātā, dayā kara more\ndante tṛṇa dhari’ ḍāke e⋅dāsa pāmare\n\npūrvete sākṣāt jata pātakī tārilā\nse vicitra nahe jāte avatāra kailā\n\nmo⋅hena pāpiṣṭhe ebe karaha uddhāra\nāścarya dayāla⋅guṇa ghuṣuka saṁsāra\n\nvicāra karile muñi nahe dayāpātra\nāpana svabhāva⋅guṇe karaha kṛtārtha\n\nviśeṣa pratijñā śuni’ ei kaliyuge\nei bharasāya rādhāmohana dayā māge",
  "translation_intro": "",
  "en_translation": "All glories, all glories to Lord Śrī Kṛṣṇa Caitanya, an ocean of mercy! All glories to the Friend of the distressed, for delivering the fallen!\n\nAll glories to the giver of loving devotion! Please bestow Your mercy upon me. This fallen servant calls out, holding a blade of grass in his teeth.\n\nIn the past, You directly delivered many sinful persons. This is not surprising, for You have appeared as an incarnation specifically for that purpose.\n\nNow, please deliver a wretch as sinful as me. Let Your astonishingly merciful qualities be proclaimed throughout the entire world.\n\nUpon reflection, I am not worthy of Your mercy. Please fulfill me by Your own merciful nature and divine qualities.\n\nHearing Your special promise in this Age of Kali, and with this hope alone, Rādhāmohana begs for Your mercy.",
  "unsorted": 1
}