{
  "author": "vaiṣṇavadāsa",
  "language": "bengali",
  "verses": "pahu̐ mora gaurāṅga gosāñī\nei kṛpā kara jena tomāra guṇa gāi\n\nje se kule janma hauka, je se deha pāñā\ntomāra bhakta-saṅge phiri tomāra guṇa gāiyā\n\ncirakāla āśā prabhu āchaye hiyāya\ntomāra nigūḍha līlā sphuraye āmāya\n\ntomāra nāme sadā ruci hauka mora\ntomāra guṇa-gāne jena sadāi hoi bhora\n\ntomāra guṇa gāite śunite bhakta⋅saṅge\nsāttvika vikāra ki hoibe mora aṅge\n\naśru⋅kampa⋅pulake pūribe saba tanu\nbhūmite paḍibe preme ageyāna janu\n\nje se kara prabhu, tumi ekamātra gati\nkahaye vaiṣṇavadāsa tomāya rahuka mati",
  "translation_intro": "",
  "en_translation": "My Lord, Gaurāṅga Gosāñī! Please grant me this mercy, so that I may sing Your glories.\n\nWhatever family I may be born into, whatever body I may attain, may I always wander in the company of Your devotees, singing Your glories.\n\nO Lord, this hope remains forever in my heart, that Your confidential pastimes may manifest within me.\n\nMay I always have a taste for Your Holy Name, and may I always be absorbed in singing Your glories.\n\nWhile singing and hearing Your glories in the company of devotees, what ecstatic transformations will manifest in my body!\n\nMy whole body will be filled with tears, trembling, and ecstatic bliss. I will fall to the ground, unconscious due to divine love.\n\nWhatever You do, O Lord, You are my only refuge. Vaiṣṇava Dāsa says: \"May my mind remain fixed on You.\"",
  "unsorted": 1
}